polygon/__init__.py
polygon/exceptions.py
polygon/logging.py
polygon/modelclass.py
polygon/rest/__init__.py
polygon/rest/aggs.py
polygon/rest/base.py
polygon/rest/benzinga.py
polygon/rest/economy.py
polygon/rest/financials.py
polygon/rest/futures.py
polygon/rest/indicators.py
polygon/rest/models/__init__.py
polygon/rest/models/aggs.py
polygon/rest/models/benzinga.py
polygon/rest/models/common.py
polygon/rest/models/conditions.py
polygon/rest/models/contracts.py
polygon/rest/models/dividends.py
polygon/rest/models/economy.py
polygon/rest/models/exchanges.py
polygon/rest/models/financials.py
polygon/rest/models/futures.py
polygon/rest/models/indicators.py
polygon/rest/models/markets.py
polygon/rest/models/quotes.py
polygon/rest/models/request.py
polygon/rest/models/snapshot.py
polygon/rest/models/splits.py
polygon/rest/models/summaries.py
polygon/rest/models/tickers.py
polygon/rest/models/tmx.py
polygon/rest/models/trades.py
polygon/rest/quotes.py
polygon/rest/reference.py
polygon/rest/snapshot.py
polygon/rest/summaries.py
polygon/rest/tmx.py
polygon/rest/trades.py
polygon/rest/vX.py
polygon/websocket/__init__.py
polygon/websocket/models/__init__.py
polygon/websocket/models/common.py
polygon/websocket/models/models.py
polygon_api_client-1.16.0.dist-info/METADATA
polygon_api_client-1.16.0.dist-info/WHEEL
polygon_api_client-1.16.0.dist-info/licenses/LICENSE
polygon_api_client-1.16.0.dist-info/RECORD
